bambucontroll/__init__.py
bambucontroll/printer.py
bambucontroll/push.gcode
BambuControll-0.0.6.dist-info/METADATA
BambuControll-0.0.6.dist-info/WHEEL
BambuControll-0.0.6.dist-info/top_level.txt
BambuControll-0.0.6.dist-info/RECORD
