Metadata-Version: 2.1
Name: BambuControll
Version: 0.0.6
Summary: Python package for controlling Bambu Lab 3D printers (P1 and A1 series) via MQTT
Home-page: UNKNOWN
Author: CekLuka
Author-email: jaz@cekluka.com
License: UNKNOWN
Keywords: python,Bambu,3D printer,MQTT,Printer avtomation
Platform: UNKNOWN
Classifier: Development Status :: 1 - Planning
Classifier: Intended Audience :: Developers
Classifier: Programming Language :: Python :: 3
Classifier: Operating System :: Unix
Classifier: Operating System :: MacOS :: MacOS X
Classifier: Operating System :: Microsoft :: Windows
Requires-Dist: paho-mqtt
